{
    "required": true,
    "minVersion": "0.8",
    "package": "net.swedz.intothetwilight.mixin",
    "compatibilityLevel": "JAVA_17",
    "mixins": [
        "mi.MIBlastFurnaceTierMixin",
        "mi.MIMakeWaterPumpsRequireWaterBiomeMixin",
        "mi.MIMultiblockMachinesMixin",
        "mi.MISingleBlockCraftingMachinesMixin",
        "mi.MISingleBlockSpecialMachinesMixin"
    ],
    "client": [
        "client.mi.MIGuiComponentsClientMixin"
    ],
    "injectors": {
        "defaultRequire": 1
    }
}
